familyledger/VERSION
familyledger/__init__.py
familyledger/_config.py
familyledger/account.py
familyledger/commandline.py
familyledger/config.py
familyledger/dataview.py
familyledger/ledger.py
familyledger/ledger_web.py
familyledger/possessions.py
familyledger/requirements.txt
familyledger/version.py
familyledger/remi/res/font.woff2
familyledger/remi/res/style.css
familyledger/share/locale/en/LC_MESSAGES/ledger.mo
familyledger/share/locale/en/LC_MESSAGES/ledger.po
familyledger/share/locale/en/LC_MESSAGES/ledger_web.mo
familyledger/share/locale/en/LC_MESSAGES/ledger_web.po
familyledger/slpp/LICENSE
familyledger/slpp/README.markdown
familyledger/slpp/setup.py
familyledger/slpp/slpp.py
familyledger/slpp/tests.py
familyledger/utils/__init__.py
familyledger/utils/_console.py
familyledger/utils/_exception.py
familyledger/utils/_file.py
familyledger/utils/_i18n.py
familyledger/utils/_iterable.py
familyledger/utils/_logging.py
familyledger/utils/_path.py
familyledger/utils/_timer.py
familyledger/utils/_warcraft.py
familyledger/utils/warcraft.py
FamilyLedger-0.2.0.dist-info/AUTHORS
FamilyLedger-0.2.0.dist-info/LICENSE
FamilyLedger-0.2.0.dist-info/METADATA
FamilyLedger-0.2.0.dist-info/WHEEL
FamilyLedger-0.2.0.dist-info/entry_points.txt
FamilyLedger-0.2.0.dist-info/top_level.txt
FamilyLedger-0.2.0.dist-info/RECORD
