Metadata-Version: 2.1
Name: FamilyLedger
Version: 0.2.0
Summary: Family Ledger is an application for collecting and viewing in-game item data held in World of Warcraft accounts.
Home-page: https://github.com/fondlez/familyledger
Author: fondlez
Author-email: fondlez@protonmail.com
License: UNKNOWN
Download-URL: https://github.com/fondlez/familyledger
Platform: UNKNOWN
Classifier: Development Status :: 3 - Alpha
Classifier: Environment :: Console
Classifier: Environment :: Web Environment
Classifier: Intended Audience :: End Users/Desktop
Classifier: License :: OSI Approved :: GNU Lesser General Public License v3 (LGPLv3)
Classifier: Operating System :: Microsoft :: Windows
Classifier: Programming Language :: Python :: 3.4
Classifier: Topic :: Text Processing
Classifier: Topic :: Games/Entertainment :: Role-Playing
Requires-Dist: remi (==2019.11)
Requires-Dist: tqdm
Requires-Dist: XlsxWriter
